referredby/__init__.py
referredby/engines.py
referredby-0.1.4.dist-info/DESCRIPTION.rst
referredby-0.1.4.dist-info/METADATA
referredby-0.1.4.dist-info/metadata.json
referredby-0.1.4.dist-info/RECORD
referredby-0.1.4.dist-info/top_level.txt
referredby-0.1.4.dist-info/WHEEL
