Metadata-Version: 2.0
Name: referredby
Version: 0.1.4
Summary: Parsing referrer URLS for common search engines.
Home-page: http://github.com/larsyencken/referredby/
Author: Lars Yencken
Author-email: lars@yencken.org
License: ISC
Platform: UNKNOWN
Classifier: Development Status :: 4 - Beta
Classifier: Intended Audience :: Developers
Classifier: License :: OSI Approved :: ISC License (ISCL)
Classifier: Natural Language :: English
Classifier: Programming Language :: Python :: 2
Classifier: Programming Language :: Python :: 2.6
Classifier: Programming Language :: Python :: 2.7
Classifier: Programming Language :: Python :: 3
Classifier: Programming Language :: Python :: 3.3
Classifier: Programming Language :: Python :: 3.4
